xbool/__init__.py
xbool-1.1.0.dist-info/LICENSE
xbool-1.1.0.dist-info/METADATA
xbool-1.1.0.dist-info/WHEEL
xbool-1.1.0.dist-info/RECORD
