Metadata-Version: 2.1
Name: xbool
Version: 1.1.0
Summary: General purpose bool/boolean utilities, extracting bools from strings.
Home-page: https://github.com/xyngular/py-xbool
Keywords: bool,booltostr,str,environmental variable,utilites
Author: Josh Orr
Author-email: josh@orr.blue
Requires-Python: >=3.10,<4.0
Classifier: License :: OSI Approved :: The Unlicense (Unlicense)
Classifier: Programming Language :: Python :: 3
Classifier: Programming Language :: Python :: 3.10
Classifier: Programming Language :: Python :: 3.11
Classifier: Programming Language :: Python :: 3.12
Classifier: Topic :: Software Development :: Libraries :: Python Modules
Project-URL: Repository, https://github.com/xyngular/py-xbool
